lab_3/Comparator.sv
module Comparator #(parameter N = 10) (

	input [N-1:0] A, B,
	output logic equ
);

assign equ = (A==B);



endmodule

lab_3/Register.sv
module Register #(parameter N = 10) (

	input clk, rst,
	input [N-1:0] D,
	output logic [N-1:0] Q

);


always_ff @(posedge clk or posedge rst)
	if(rst) Q <= 10'h00;
	else
		Q <= D;



endmodule

lab_3/Counter.sv
module Counter #(parameter N=10)(
    input logic clk,
    input logic rst,
    input logic en,
    output logic [N-1:0] Q
);

    always_ff @(posedge clk or posedge rst) begin
        if (rst)
            Q <= 10'h00;  // asigna cero compatible con cualquier tamaño
        else if (en)
            Q <= Q + 1'b1;
    end

endmodule

lab_3/Vga_Controller.sv
module Vga_Controller #(parameter N=8)(
    input logic clk, rst,
    output logic Hs, Vs,
    output logic [7:0] R, G, B,
	 output logic [9:0] Q_xz,
	 output logic [9:0] Q_yz
	 
);	 

	logic [9:0] Q_x, Q_y, D_x, D_y;         
   logic rstx,rsty;

	Counter count_y(clk, (rstx & rsty)| rst, rstx, D_y);			
	Counter count_x(clk, rstx | rst , 1'b1, D_x);
   

	Register reg_x(clk, rst, D_x, Q_x);
	Register reg_y(clk, rst, D_y, Q_y);
	
	Comparator cmp_x(Q_x, 10'd800, rstx);
	Comparator cmp_y(Q_y, 10'd525, rsty);

    
    

    // Señales de sincronización
    assign Hs = ~(Q_x >= 656 && Q_x < 752);  // Pulso horizontal activo en bajo
	 assign Vs = ~(Q_y >= 490 && Q_y < 492);  // Pulso vertical activo en bajo  
	 assign Q_xz = Q_x;
	 assign Q_yz = Q_y;
	 
	  assign R = (Q_x < 640 && Q_y < 480) ? 8'b10110000 : 8'h00;
	  assign G = (Q_x < 640 && Q_y < 480) ? 8'b10110000 : 8'h00;
	  assign B = (Q_x < 640 && Q_y < 480) ? 8'b10110000 : 8'h00;
	 

    // Zona visible y color
	 

//	 always_comb begin
//        if (Q_x >= 270 && Q_x < 370 && Q_y >= 190 && Q_y < 290) begin
//			 R = 8'hFF;
//			 G = 8'h00;
//			 B = 8'h00;
//        end else begin
//            R = 8'h00;
//            G = 8'h00;
//            B = 8'h00;
//        end
//		  
//	end


endmodule

lab_3/tb_Vga_Controller.sv
module tb_Vga_Controller;

    logic clk;
    logic rst;

    logic Hs, Vs;
    logic [7:0] R, G, B;
    logic [9:0] Q_xz;
    logic [9:0] Q_yz;

    Vga_Controller uut (
        .clk(clk),
        .rst(rst),
        .Hs(Hs),
        .Vs(Vs),
        .R(R),
        .G(G),
        .B(B),
        .Q_xz(Q_xz),
        .Q_yz(Q_yz)
    );

    // Reloj de 25 MHz
    initial begin
        clk = 0;
        forever #20 clk = ~clk;
    end

    // Estimulación
    initial begin
    rst = 0;
    #10 rst = 1;
    #10 rst = 0;


    #200_000;  
    $finish;
	end

    // Monitor
    initial begin
        $monitor("t=%0t | Hs=%b Vs=%b | R=%h G=%h B=%h | Qx=%d Qy=%d",
                 $time, Hs, Vs, R, G, B, Q_xz, Q_yz);
    end

    // Dump para GTKWave
    initial begin
        $dumpfile("vga_controller_tb.vcd");
        $dumpvars(0, tb_Vga_Controller);
    end

endmodule

lab_3/simulation/modelsim/vga_controller_tb.vcd
$date
	Sun Apr 06 14:26:04 2025
$end
$version
	ModelSim Version 10.5b
$end
$timescale
	1ps
$end

$scope module tb_Vga_Controller $end
$var reg 1 ! clk $end
$var reg 1 " rst $end
$var reg 1 # Hs $end
$var reg 1 $ Vs $end
$var reg 8 % R [7:0] $end
$var reg 8 & G [7:0] $end
$var reg 8 ' B [7:0] $end
$var reg 10 ( Q_xz [9:0] $end
$var reg 10 ) Q_yz [9:0] $end

$scope module uut $end
$var parameter 32 * N $end
$var wire 1 + clk $end
$var wire 1 , rst $end
$var reg 1 - Hs $end
$var reg 1 . Vs $end
$var reg 8 / R [7:0] $end
$var reg 8 0 G [7:0] $end
$var reg 8 1 B [7:0] $end
$var reg 10 2 Q_xz [9:0] $end
$var reg 10 3 Q_yz [9:0] $end
$var reg 10 4 Q_x [9:0] $end
$var reg 10 5 Q_y [9:0] $end
$var reg 10 6 D_x [9:0] $end
$var reg 10 7 D_y [9:0] $end
$var reg 1 8 rstx $end
$var reg 1 9 rsty $end

$scope module count_y $end
$var parameter 32 : N $end
$var wire 1 + clk $end
$var wire 1 ; rst $end
$var wire 1 < en $end
$var reg 10 = Q [9:0] $end
$upscope $end

$scope module count_x $end
$var parameter 32 > N $end
$var wire 1 + clk $end
$var wire 1 ? rst $end
$var wire 1 @ en $end
$var reg 10 A Q [9:0] $end
$upscope $end

$scope module reg_x $end
$var parameter 32 B N $end
$var wire 1 + clk $end
$var wire 1 , rst $end
$var wire 1 C D [9] $end
$var wire 1 D D [8] $end
$var wire 1 E D [7] $end
$var wire 1 F D [6] $end
$var wire 1 G D [5] $end
$var wire 1 H D [4] $end
$var wire 1 I D [3] $end
$var wire 1 J D [2] $end
$var wire 1 K D [1] $end
$var wire 1 L D [0] $end
$var reg 10 M Q [9:0] $end
$upscope $end

$scope module reg_y $end
$var parameter 32 N N $end
$var wire 1 + clk $end
$var wire 1 , rst $end
$var wire 1 O D [9] $end
$var wire 1 P D [8] $end
$var wire 1 Q D [7] $end
$var wire 1 R D [6] $end
$var wire 1 S D [5] $end
$var wire 1 T D [4] $end
$var wire 1 U D [3] $end
$var wire 1 V D [2] $end
$var wire 1 W D [1] $end
$var wire 1 X D [0] $end
$var reg 10 Y Q [9:0] $end
$upscope $end

$scope module cmp_x $end
$var parameter 32 Z N $end
$var wire 1 [ A [9] $end
$var wire 1 \ A [8] $end
$var wire 1 ] A [7] $end
$var wire 1 ^ A [6] $end
$var wire 1 _ A [5] $end
$var wire 1 ` A [4] $end
$var wire 1 a A [3] $end
$var wire 1 b A [2] $end
$var wire 1 c A [1] $end
$var wire 1 d A [0] $end
$var wire 1 e B [9] $end
$var wire 1 f B [8] $end
$var wire 1 g B [7] $end
$var wire 1 h B [6] $end
$var wire 1 i B [5] $end
$var wire 1 j B [4] $end
$var wire 1 k B [3] $end
$var wire 1 l B [2] $end
$var wire 1 m B [1] $end
$var wire 1 n B [0] $end
$var reg 1 o equ $end
$upscope $end

$scope module cmp_y $end
$var parameter 32 p N $end
$var wire 1 q A [9] $end
$var wire 1 r A [8] $end
$var wire 1 s A [7] $end
$var wire 1 t A [6] $end
$var wire 1 u A [5] $end
$var wire 1 v A [4] $end
$var wire 1 w A [3] $end
$var wire 1 x A [2] $end
$var wire 1 y A [1] $end
$var wire 1 z A [0] $end
$var wire 1 { B [9] $end
$var wire 1 | B [8] $end
$var wire 1 } B [7] $end
$var wire 1 ~ B [6] $end
$var wire 1 !! B [5] $end
$var wire 1 "! B [4] $end
$var wire 1 #! B [3] $end
$var wire 1 $! B [2] $end
$var wire 1 %! B [1] $end
$var wire 1 &! B [0] $end
$var reg 1 '! equ $end
$upscope $end
$upscope $end
$upscope $end
$enddefinitions $end
#0
$dumpvars
0!
0"
x#
x$
b11111111 %
b11111111 &
b11111111 '
bx (
bx )
x-
x.
b11111111 /
b11111111 0
b11111111 1
bx 2
bx 3
bx 4
bx 5
bx 6
bx 7
x8
x9
bx =
bx A
bx M
bx Y
xo
x'!
b1000 *
b1010 :
b1010 >
b1010 B
b1010 N
b1010 Z
b1010 p
0+
0,
1&!
0%!
1$!
1#!
0"!
0!!
0~
0}
0|
1{
0n
0m
0l
0k
0j
1i
0h
0g
1f
1e
1@
x?
x;
x<
xL
xK
xJ
xI
xH
xG
xF
xE
xD
xC
xX
xW
xV
xU
xT
xS
xR
xQ
xP
xO
xd
xc
xb
xa
x`
x_
x^
x]
x\
x[
xz
xy
xx
xw
xv
xu
xt
xs
xr
xq
$end
#10
1"
1,
1;
1?
b0 A
b0 =
b0 M
b0 Y
b0 5
b0 4
b0 7
b0 6
b0 2
1-
b0 3
1.
0L
0K
0J
0I
0H
0G
0F
0E
0D
0C
0X
0W
0V
0U
0T
0S
0R
0Q
0P
0O
0d
0c
0b
0a
0`
0_
0^
0]
0\
0[
0z
0y
0x
0w
0v
0u
0t
0s
0r
0q
0'!
0o
1$
b0 )
1#
b0 (
08
09
0<
#20
1!
0"
1+
0,
0;
0?
b1 A
b1 6
1L
#40
0!
0+
#60
1!
1+
b10 A
b1 M
b1 4
b10 6
b1 2
0L
1K
1d
b1 (
#80
0!
0+
#100
1!
1+
b11 A
b10 M
b10 4
b11 6
b10 2
1L
0d
1c
b10 (
#120
0!
0+
#140
1!
1+
b100 A
b11 M
b11 4
b100 6
b11 2
0L
0K
1J
1d
b11 (
#160
0!
0+
#180
1!
1+
b101 A
b100 M
b100 4
b101 6
b100 2
1L
0d
0c
1b
b100 (
#200
0!
0+
#220
1!
1+
b110 A
b101 M
b101 4
b110 6
b101 2
0L
1K
1d
b101 (
#240
0!
0+
#260
1!
1+
b111 A
b110 M
b110 4
b111 6
b110 2
1L
0d
1c
b110 (
#280
0!
0+
#300
1!
1+
b1000 A
b111 M
b111 4
b1000 6
b111 2
0L
0K
0J
1I
1d
b111 (
#320
0!
0+
#340
1!
1+
b1001 A
b1000 M
b1000 4
b1001 6
b1000 2
1L
0d
0c
0b
1a
b1000 (
#360
0!
0+
#380
1!
1+
b1010 A
b1001 M
b1001 4
b1010 6
b1001 2
0L
1K
1d
b1001 (
#400
0!
0+
#420
1!
1+
b1011 A
b1010 M
b1010 4
b1011 6
b1010 2
1L
0d
1c
b1010 (
#440
0!
0+
#460
1!
1+
b1100 A
b1011 M
b1011 4
b1100 6
b1011 2
0L
0K
1J
1d
b1011 (
#480
0!
0+
#500
1!
1+
b1101 A
b1100 M
b1100 4
b1101 6
b1100 2
1L
0d
0c
1b
b1100 (
#520
0!
0+
#540
1!
1+
b1110 A
b1101 M
b1101 4
b1110 6
b1101 2
0L
1K
1d
b1101 (
#560
0!
0+
#580
1!
1+
b1111 A
b1110 M
b1110 4
b1111 6
b1110 2
1L
0d
1c
b1110 (
#600
0!
0+
#620
1!
1+
b10000 A
b1111 M
b1111 4
b10000 6
b1111 2
0L
0K
0J
0I
1H
1d
b1111 (
#640
0!
0+
#660
1!
1+
b10001 A
b10000 M
b10000 4
b10001 6
b10000 2
1L
0d
0c
0b
0a
1`
b10000 (
#680
0!
0+
#700
1!
1+
b10010 A
b10001 M
b10001 4
b10010 6
b10001 2
0L
1K
1d
b10001 (
#720
0!
0+
#740
1!
1+
b10011 A
b10010 M
b10010 4
b10011 6
b10010 2
1L
0d
1c
b10010 (
#760
0!
0+
#780
1!
1+
b10100 A
b10011 M
b10011 4
b10100 6
b10011 2
0L
0K
1J
1d
b10011 (
#800
0!
0+
#820
1!
1+
b10101 A
b10100 M
b10100 4
b10101 6
b10100 2
1L
0d
0c
1b
b10100 (
#840
0!
0+
#860
1!
1+
b10110 A
b10101 M
b10101 4
b10110 6
b10101 2
0L
1K
1d
b10101 (
#880
0!
0+
#900
1!
1+
b10111 A
b10110 M
b10110 4
b10111 6
b10110 2
1L
0d
1c
b10110 (
#920
0!
0+
#940
1!
1+
b11000 A
b10111 M
b10111 4
b11000 6
b10111 2
0L
0K
0J
1I
1d
b10111 (
#960
0!
0+
#980
1!
1+
b11001 A
b11000 M
b11000 4
b11001 6
b11000 2
1L
0d
0c
0b
1a
b11000 (
#1000
0!
0+
#1020
1!
1+
b11010 A
b11001 M
b11001 4
b11010 6
b11001 2
0L
1K
1d
b11001 (
#1040
0!
0+
#1060
1!
1+
b11011 A
b11010 M
b11010 4
b11011 6
b11010 2
1L
0d
1c
b11010 (
#1080
0!
0+
#1100
1!
1+
b11100 A
b11011 M
b11011 4
b11100 6
b11011 2
0L
0K
1J
1d
b11011 (
#1120
0!
0+
#1140
1!
1+
b11101 A
b11100 M
b11100 4
b11101 6
b11100 2
1L
0d
0c
1b
b11100 (
#1160
0!
0+
#1180
1!
1+
b11110 A
b11101 M
b11101 4
b11110 6
b11101 2
0L
1K
1d
b11101 (
#1200
0!
0+
#1220
1!
1+
b11111 A
b11110 M
b11110 4
b11111 6
b11110 2
1L
0d
1c
b11110 (
#1240
0!
0+
#1260
1!
1+
b100000 A
b11111 M
b11111 4
b100000 6
b11111 2
0L
0K
0J
0I
0H
1G
1d
b11111 (
#1280
0!
0+
#1300
1!
1+
b100001 A
b100000 M
b100000 4
b100001 6
b100000 2
1L
0d
0c
0b
0a
0`
1_
b100000 (
#1320
0!
0+
#1340
1!
1+
b100010 A
b100001 M
b100001 4
b100010 6
b100001 2
0L
1K
1d
b100001 (
#1360
0!
0+
#1380
1!
1+
b100011 A
b100010 M
b100010 4
b100011 6
b100010 2
1L
0d
1c
b100010 (
#1400
0!
0+
#1420
1!
1+
b100100 A
b100011 M
b100011 4
b100100 6
b100011 2
0L
0K
1J
1d
b100011 (
#1440
0!
0+
#1460
1!
1+
b100101 A
b100100 M
b100100 4
b100101 6
b100100 2
1L
0d
0c
1b
b100100 (
#1480
0!
0+
#1500
1!
1+
b100110 A
b100101 M
b100101 4
b100110 6
b100101 2
0L
1K
1d
b100101 (
#1520
0!
0+
#1540
1!
1+
b100111 A
b100110 M
b100110 4
b100111 6
b100110 2
1L
0d
1c
b100110 (
#1560
0!
0+
#1580
1!
1+
b101000 A
b100111 M
b100111 4
b101000 6
b100111 2
0L
0K
0J
1I
1d
b100111 (
#1600
0!
0+
#1620
1!
1+
b101001 A
b101000 M
b101000 4
b101001 6
b101000 2
1L
0d
0c
0b
1a
b101000 (
#1640
0!
0+
#1660
1!
1+
b101010 A
b101001 M
b101001 4
b101010 6
b101001 2
0L
1K
1d
b101001 (
#1680
0!
0+
#1700
1!
1+
b101011 A
b101010 M
b101010 4
b101011 6
b101010 2
1L
0d
1c
b101010 (
#1720
0!
0+
#1740
1!
1+
b101100 A
b101011 M
b101011 4
b101100 6
b101011 2
0L
0K
1J
1d
b101011 (
#1760
0!
0+
#1780
1!
1+
b101101 A
b101100 M
b101100 4
b101101 6
b101100 2
1L
0d
0c
1b
b101100 (
#1800
0!
0+
#1820
1!
1+
b101110 A
b101101 M
b101101 4
b101110 6
b101101 2
0L
1K
1d
b101101 (
#1840
0!
0+
#1860
1!
1+
b101111 A
b101110 M
b101110 4
b101111 6
b101110 2
1L
0d
1c
b101110 (
#1880
0!
0+
#1900
1!
1+
b110000 A
b101111 M
b101111 4
b110000 6
b101111 2
0L
0K
0J
0I
1H
1d
b101111 (
#1920
0!
0+
#1940
1!
1+
b110001 A
b110000 M
b110000 4
b110001 6
b110000 2
1L
0d
0c
0b
0a
1`
b110000 (
#1960
0!
0+
#1980
1!
1+
b110010 A
b110001 M
b110001 4
b110010 6
b110001 2
0L
1K
1d
b110001 (
#2000
0!
0+
#2020
1!
1+
b110011 A
b110010 M
b110010 4
b110011 6
b110010 2
1L
0d
1c
b110010 (
#2040
0!
0+
#2060
1!
1+
b110100 A
b110011 M
b110011 4
b110100 6
b110011 2
0L
0K
1J
1d
b110011 (
#2080
0!
0+
#2100
1!
1+
b110101 A
b110100 M
b110100 4
b110101 6
b110100 2
1L
0d
0c
1b
b110100 (
#2120
0!
0+
#2140
1!
1+
b110110 A
b110101 M
b110101 4
b110110 6
b110101 2
0L
1K
1d
b110101 (
#2160
0!
0+
#2180
1!
1+
b110111 A
b110110 M
b110110 4
b110111 6
b110110 2
1L
0d
1c
b110110 (
#2200
0!
0+
#2220
1!
1+
b111000 A
b110111 M
b110111 4
b111000 6
b110111 2
0L
0K
0J
1I
1d
b110111 (
#2240
0!
0+
#2260
1!
1+
b111001 A
b111000 M
b111000 4
b111001 6
b111000 2
1L
0d
0c
0b
1a
b111000 (
#2280
0!
0+
#2300
1!
1+
b111010 A
b111001 M
b111001 4
b111010 6
b111001 2
0L
1K
1d
b111001 (
#2320
0!
0+
#2340
1!
1+
b111011 A
b111010 M
b111010 4
b111011 6
b111010 2
1L
0d
1c
b111010 (
#2360
0!
0+
#2380
1!
1+
b111100 A
b111011 M
b111011 4
b111100 6
b111011 2
0L
0K
1J
1d
b111011 (
#2400
0!
0+
#2420
1!
1+
b111101 A
b111100 M
b111100 4
b111101 6
b111100 2
1L
0d
0c
1b
b111100 (
#2440
0!
0+
#2460
1!
1+
b111110 A
b111101 M
b111101 4
b111110 6
b111101 2
0L
1K
1d
b111101 (
#2480
0!
0+
#2500
1!
1+
b111111 A
b111110 M
b111110 4
b111111 6
b111110 2
1L
0d
1c
b111110 (
#2520
0!
0+
#2540
1!
1+
b1000000 A
b111111 M
b111111 4
b1000000 6
b111111 2
0L
0K
0J
0I
0H
0G
1F
1d
b111111 (
#2560
0!
0+
#2580
1!
1+
b1000001 A
b1000000 M
b1000000 4
b1000001 6
b1000000 2
1L
0d
0c
0b
0a
0`
0_
1^
b1000000 (
#2600
0!
0+
#2620
1!
1+
b1000010 A
b1000001 M
b1000001 4
b1000010 6
b1000001 2
0L
1K
1d
b1000001 (
#2640
0!
0+
#2660
1!
1+
b1000011 A
b1000010 M
b1000010 4
b1000011 6
b1000010 2
1L
0d
1c
b1000010 (
#2680
0!
0+
#2700
1!
1+
b1000100 A
b1000011 M
b1000011 4
b1000100 6
b1000011 2
0L
0K
1J
1d
b1000011 (
#2720
0!
0+
#2740
1!
1+
b1000101 A
b1000100 M
b1000100 4
b1000101 6
b1000100 2
1L
0d
0c
1b
b1000100 (
#2760
0!
0+
#2780
1!
1+
b1000110 A
b1000101 M
b1000101 4
b1000110 6
b1000101 2
0L
1K
1d
b1000101 (
#2800
0!
0+
#2820
1!
1+
b1000111 A
b1000110 M
b1000110 4
b1000111 6
b1000110 2
1L
0d
1c
b1000110 (
#2840
0!
0+
#2860
1!
1+
b1001000 A
b1000111 M
b1000111 4
b1001000 6
b1000111 2
0L
0K
0J
1I
1d
b1000111 (
#2880
0!
0+
#2900
1!
1+
b1001001 A
b1001000 M
b1001000 4
b1001001 6
b1001000 2
1L
0d
0c
0b
1a
b1001000 (
#2920
0!
0+
#2940
1!
1+
b1001010 A
b1001001 M
b1001001 4
b1001010 6
b1001001 2
0L
1K
1d
b1001001 (
#2960
0!
0+
#2980
1!
1+
b1001011 A
b1001010 M
b1001010 4
b1001011 6
b1001010 2
1L
0d
1c
b1001010 (
#3000
0!
0+
#3020
1!
1+
b1001100 A
b1001011 M
b1001011 4
b1001100 6
b1001011 2
0L
0K
1J
1d
b1001011 (
#3040
0!
0+
#3060
1!
1+
b1001101 A
b1001100 M
b1001100 4
b1001101 6
b1001100 2
1L
0d
0c
1b
b1001100 (
#3080
0!
0+
#3100
1!
1+
b1001110 A
b1001101 M
b1001101 4
b1001110 6
b1001101 2
0L
1K
1d
b1001101 (
#3120
0!
0+
#3140
1!
1+
b1001111 A
b1001110 M
b1001110 4
b1001111 6
b1001110 2
1L
0d
1c
b1001110 (
#3160
0!
0+
#3180
1!
1+
b1010000 A
b1001111 M
b1001111 4
b1010000 6
b1001111 2
0L
0K
0J
0I
1H
1d
b1001111 (
#3200
0!
0+
#3220
1!
1+
b1010001 A
b1010000 M
b1010000 4
b1010001 6
b1010000 2
1L
0d
0c
0b
0a
1`
b1010000 (
#3240
0!
0+
#3260
1!
1+
b1010010 A
b1010001 M
b1010001 4
b1010010 6
b1010001 2
0L
1K
1d
b1010001 (
#3280
0!
0+
#3300
1!
1+
b1010011 A
b1010010 M
b1010010 4
b1010011 6
b1010010 2
1L
0d
1c
b1010010 (
#3320
0!
0+
#3340
1!
1+
b1010100 A
b1010011 M
b1010011 4
b1010100 6
b1010011 2
0L
0K
1J
1d
b1010011 (
#3360
0!
0+
#3380
1!
1+
b1010101 A
b1010100 M
b1010100 4
b1010101 6
b1010100 2
1L
0d
0c
1b
b1010100 (
#3400
0!
0+
#3420
1!
1+
b1010110 A
b1010101 M
b1010101 4
b1010110 6
b1010101 2
0L
1K
1d
b1010101 (
#3440
0!
0+
#3460
1!
1+
b1010111 A
b1010110 M
b1010110 4
b1010111 6
b1010110 2
1L
0d
1c
b1010110 (
#3480
0!
0+
#3500
1!
1+
b1011000 A
b1010111 M
b1010111 4
b1011000 6
b1010111 2
0L
0K
0J
1I
1d
b1010111 (
#3520
0!
0+
#3540
1!
1+
b1011001 A
b1011000 M
b1011000 4
b1011001 6
b1011000 2
1L
0d
0c
0b
1a
b1011000 (
#3560
0!
0+
#3580
1!
1+
b1011010 A
b1011001 M
b1011001 4
b1011010 6
b1011001 2
0L
1K
1d
b1011001 (
#3600
0!
0+
#3620
1!
1+
b1011011 A
b1011010 M
b1011010 4
b1011011 6
b1011010 2
1L
0d
1c
b1011010 (
#3640
0!
0+
#3660
1!
1+
b1011100 A
b1011011 M
b1011011 4
b1011100 6
b1011011 2
0L
0K
1J
1d
b1011011 (
#3680
0!
0+
#3700
1!
1+
b1011101 A
b1011100 M
b1011100 4
b1011101 6
b1011100 2
1L
0d
0c
1b
b1011100 (
#3720
0!
0+
#3740
1!
1+
b1011110 A
b1011101 M
b1011101 4
b1011110 6
b1011101 2
0L
1K
1d
b1011101 (
#3760
0!
0+
#3780
1!
1+
b1011111 A
b1011110 M
b1011110 4
b1011111 6
b1011110 2
1L
0d
1c
b1011110 (
#3800
0!
0+
#3820
1!
1+
b1100000 A
b1011111 M
b1011111 4
b1100000 6
b1011111 2
0L
0K
0J
0I
0H
1G
1d
b1011111 (
#3840
0!
0+
#3860
1!
1+
b1100001 A
b1100000 M
b1100000 4
b1100001 6
b1100000 2
1L
0d
0c
0b
0a
0`
1_
b1100000 (
#3880
0!
0+
#3900
1!
1+
b1100010 A
b1100001 M
b1100001 4
b1100010 6
b1100001 2
0L
1K
1d
b1100001 (
#3920
0!
0+
#3940
1!
1+
b1100011 A
b1100010 M
b1100010 4
b1100011 6
b1100010 2
1L
0d
1c
b1100010 (
#3960
0!
0+
#3980
1!
1+
b1100100 A
b1100011 M
b1100011 4
b1100100 6
b1100011 2
0L
0K
1J
1d
b1100011 (
#4000
0!
0+
#4020
1!
1+
b1100101 A
b1100100 M
b1100100 4
b1100101 6
b1100100 2
1L
0d
0c
1b
b1100100 (
#4040
0!
0+
#4060
1!
1+
b1100110 A
b1100101 M
b1100101 4
b1100110 6
b1100101 2
0L
1K
1d
b1100101 (
#4080
0!
0+
#4100
1!
1+
b1100111 A
b1100110 M
b1100110 4
b1100111 6
b1100110 2
1L
0d
1c
b1100110 (
#4120
0!
0+
#4140
1!
1+
b1101000 A
b1100111 M
b1100111 4
b1101000 6
b1100111 2
0L
0K
0J
1I
1d
b1100111 (
#4160
0!
0+
#4180
1!
1+
b1101001 A
b1101000 M
b1101000 4
b1101001 6
b1101000 2
1L
0d
0c
0b
1a
b1101000 (
#4200
0!
0+
#4220
1!
1+
b1101010 A
b1101001 M
b1101001 4
b1101010 6
b1101001 2
0L
1K
1d
b1101001 (
#4240
0!
0+
#4260
1!
1+
b1101011 A
b1101010 M
b1101010 4
b1101011 6
b1101010 2
1L
0d
1c
b1101010 (
#4280
0!
0+
#4300
1!
1+
b1101100 A
b1101011 M
b1101011 4
b1101100 6
b1101011 2
0L
0K
1J
1d
b1101011 (
#4320
0!
0+
#4340
1!
1+
b1101101 A
b1101100 M
b1101100 4
b1101101 6
b1101100 2
1L
0d
0c
1b
b1101100 (
#4360
0!
0+
#4380
1!
1+
b1101110 A
b1101101 M
b1101101 4
b1101110 6
b1101101 2
0L
1K
1d
b1101101 (
#4400
0!
0+
#4420
1!
1+
b1101111 A
b1101110 M
b1101110 4
b1101111 6
b1101110 2
1L
0d
1c
b1101110 (
#4440
0!
0+
#4460
1!
1+
b1110000 A
b1101111 M
b1101111 4
b1110000 6
b1101111 2
0L
0K
0J
0I
1H
1d
b1101111 (
#4480
0!
0+
#4500
1!
1+
b1110001 A
b1110000 M
b1110000 4
b1110001 6
b1110000 2
1L
0d
0c
0b
0a
1`
b1110000 (
#4520
0!
0+
#4540
1!
1+
b1110010 A
b1110001 M
b1110001 4
b1110010 6
b1110001 2
0L
1K
1d
b1110001 (
#4560
0!
0+
#4580
1!
1+
b1110011 A
b1110010 M
b1110010 4
b1110011 6
b1110010 2
1L
0d
1c
b1110010 (
#4600
0!
0+
#4620
1!
1+
b1110100 A
b1110011 M
b1110011 4
b1110100 6
b1110011 2
0L
0K
1J
1d
b1110011 (
#4640
0!
0+
#4660
1!
1+
b1110101 A
b1110100 M
b1110100 4
b1110101 6
b1110100 2
1L
0d
0c
1b
b1110100 (
#4680
0!
0+
#4700
1!
1+
b1110110 A
b1110101 M
b1110101 4
b1110110 6
b1110101 2
0L
1K
1d
b1110101 (
#4720
0!
0+
#4740
1!
1+
b1110111 A
b1110110 M
b1110110 4
b1110111 6
b1110110 2
1L
0d
1c
b1110110 (
#4760
0!
0+
#4780
1!
1+
b1111000 A
b1110111 M
b1110111 4
b1111000 6
b1110111 2
0L
0K
0J
1I
1d
b1110111 (
#4800
0!
0+
#4820
1!
1+
b1111001 A
b1111000 M
b1111000 4
b1111001 6
b1111000 2
1L
0d
0c
0b
1a
b1111000 (
#4840
0!
0+
#4860
1!
1+
b1111010 A
b1111001 M
b1111001 4
b1111010 6
b1111001 2
0L
1K
1d
b1111001 (
#4880
0!
0+
#4900
1!
1+
b1111011 A
b1111010 M
b1111010 4
b1111011 6
b1111010 2
1L
0d
1c
b1111010 (
#4920
0!
0+
#4940
1!
1+
b1111100 A
b1111011 M
b1111011 4
b1111100 6
b1111011 2
0L
0K
1J
1d
b1111011 (
#4960
0!
0+
#4980
1!
1+
b1111101 A
b1111100 M
b1111100 4
b1111101 6
b1111100 2
1L
0d
0c
1b
b1111100 (
#5000
0!
0+
#5020
1!
1+
b1111110 A
b1111101 M
b1111101 4
b1111110 6
b1111101 2
0L
1K
1d
b1111101 (
#5040
0!
0+
#5060
1!
1+
b1111111 A
b1111110 M
b1111110 4
b1111111 6
b1111110 2
1L
0d
1c
b1111110 (
#5080
0!
0+
#5100
1!
1+
b10000000 A
b1111111 M
b1111111 4
b10000000 6
b1111111 2
0L
0K
0J
0I
0H
0G
0F
1E
1d
b1111111 (
#5120
0!
0+
#5140
1!
1+
b10000001 A
b10000000 M
b10000000 4
b10000001 6
b10000000 2
1L
0d
0c
0b
0a
0`
0_
0^
1]
b10000000 (
#5160
0!
0+
#5180
1!
1+
b10000010 A
b10000001 M
b10000001 4
b10000010 6
b10000001 2
0L
1K
1d
b10000001 (
#5200
0!
0+
#5220
1!
1+
b10000011 A
b10000010 M
b10000010 4
b10000011 6
b10000010 2
1L
0d
1c
b10000010 (
#5240
0!
0+
#5260
1!
1+
b10000100 A
b10000011 M
b10000011 4
b10000100 6
b10000011 2
0L
0K
1J
1d
b10000011 (
#5280
0!
0+
#5300
1!
1+
b10000101 A
b10000100 M
b10000100 4
b10000101 6
b10000100 2
1L
0d
0c
1b
b10000100 (
#5320
0!
0+
#5340
1!
1+
b10000110 A
b10000101 M
b10000101 4
b10000110 6
b10000101 2
0L
1K
1d
b10000101 (
#5360
0!
0+
#5380
1!
1+
b10000111 A
b10000110 M
b10000110 4
b10000111 6
b10000110 2
1L
0d
1c
b10000110 (
#5400
0!
0+
#5420
1!
1+
b10001000 A
b10000111 M
b10000111 4
b10001000 6
b10000111 2
0L
0K
0J
1I
1d
b10000111 (
#5440
0!
0+
#5460
1!
1+
b10001001 A
b10001000 M
b10001000 4
b10001001 6
b10001000 2
1L
0d
0c
0b
1a
b10001000 (
#5480
0!
0+
#5500
1!
1+
b10001010 A
b10001001 M
b10001001 4
b10001010 6
b10001001 2
0L
1K
1d
b10001001 (
#5520
0!
0+
#5540
1!
1+
b10001011 A
b10001010 M
b10001010 4
b10001011 6
b10001010 2
1L
0d
1c
b10001010 (
#5560
0!
0+
#5580
1!
1+
b10001100 A
b10001011 M
b10001011 4
b10001100 6
b10001011 2
0L
0K
1J
1d
b10001011 (
#5600
0!
0+
#5620
1!
1+
b10001101 A
b10001100 M
b10001100 4
b10001101 6
b10001100 2
1L
0d
0c
1b
b10001100 (
#5640
0!
0+
#5660
1!
1+
b10001110 A
b10001101 M
b10001101 4
b10001110 6
b10001101 2
0L
1K
1d
b10001101 (
#5680
0!
0+
#5700
1!
1+
b10001111 A
b10001110 M
b10001110 4
b10001111 6
b10001110 2
1L
0d
1c
b10001110 (
#5720
0!
0+
#5740
1!
1+
b10010000 A
b10001111 M
b10001111 4
b10010000 6
b10001111 2
0L
0K
0J
0I
1H
1d
b10001111 (
#5760
0!
0+
#5780
1!
1+
b10010001 A
b10010000 M
b10010000 4
b10010001 6
b10010000 2
1L
0d
0c
0b
0a
1`
b10010000 (
#5800
0!
0+
#5820
1!
1+
b10010010 A
b10010001 M
b10010001 4
b10010010 6
b10010001 2
0L
1K
1d
b10010001 (
#5840
0!
0+
#5860
1!
1+
b10010011 A
b10010010 M
b10010010 4
b10010011 6
b10010010 2
1L
0d
1c
b10010010 (
#5880
0!
0+
#5900
1!
1+
b10010100 A
b10010011 M
b10010011 4
b10010100 6
b10010011 2
0L
0K
1J
1d
b10010011 (
#5920
0!
0+
#5940
1!
1+
b10010101 A
b10010100 M
b10010100 4
b10010101 6
b10010100 2
1L
0d
0c
1b
b10010100 (
#5960
0!
0+
#5980
1!
1+
b10010110 A
b10010101 M
b10010101 4
b10010110 6
b10010101 2
0L
1K
1d
b10010101 (
#6000
0!
0+
#6020
1!
1+
b10010111 A
b10010110 M
b10010110 4
b10010111 6
b10010110 2
1L
0d
1c
b10010110 (
#6040
0!
0+
#6060
1!
1+
b10011000 A
b10010111 M
b10010111 4
b10011000 6
b10010111 2
0L
0K
0J
1I
1d
b10010111 (
#6080
0!
0+
#6100
1!
1+
b10011001 A
b10011000 M
b10011000 4
b10011001 6
b10011000 2
1L
0d
0c
0b
1a
b10011000 (
#6120
0!
0+
#6140
1!
1+
b10011010 A
b10011001 M
b10011001 4
b10011010 6
b10011001 2
0L
1K
1d
b10011001 (
#6160
0!
0+
